tests
pyjsiocompile
